gleqpy
gleqpy/ase/
gleqpy/md/
gleqpy/memory/
