Metadata-Version: 2.1
Name: GLEqPy
Version: 1.0.3
Summary: Tools for generalized Langevin equation simulation and analysis
Home-page: https://github.com/afarahva/gleqpy/
Author: Ardavan Farahvash
Author-email: ardavanf95@gmail.com
Maintainer: Ardavan Farahvash
Maintainer-email: ardavanf95@gmail.com
License: MIT
Keywords: generalized-langevin-equation,langevin,molecular-dynamics,atomic-simulation-environment,python
Classifier: License :: OSI Approved :: MIT License
Classifier: Programming Language :: Python :: 3
License-File: LICENSE.md
